stochastiCV/__init__.py
stochastiCV/_utils.py
stochastiCV/kfolds.py
stochastiCV/straight.py
stochastiCV/subsample.py
stochastiCV-0.2.1.post1.dist-info/LICENSE
stochastiCV-0.2.1.post1.dist-info/METADATA
stochastiCV-0.2.1.post1.dist-info/WHEEL
stochastiCV-0.2.1.post1.dist-info/top_level.txt
stochastiCV-0.2.1.post1.dist-info/RECORD
