Metadata-Version: 2.1
Name: stochastiCV
Version: 0.2.1.post1
Summary: A method of cross-validation based on scikit-learn that splits data into subsampling or k-folds splits (using random or assigned seed values) and then repeats the model multiple times using different seeds. This function enables a more statistical and scientific method of investigating model performance.
Home-page: https://github.com/mjkleiman/stochastiCV
Author: Michael J Kleiman
Author-email: michael@kleiman.me
License: BSD-3
Project-URL: Issue Tracker, https://github.com/mjkleiman/stochastiCV/issues
Platform: UNKNOWN
License-File: LICENSE
